partial_json_parser-0.2.1.1.post4.dist-info/METADATA
partial_json_parser-0.2.1.1.post4.dist-info/WHEEL
partial_json_parser-0.2.1.1.post4.dist-info/entry_points.txt
partial_json_parser/__init__.py
partial_json_parser/core/api.py
partial_json_parser/core/complete.py
partial_json_parser/core/exceptions.py
partial_json_parser/core/myelin.py
partial_json_parser/core/options.py
partial_json_parser/options.py
partial_json_parser/playground.py
partial_json_parser-0.2.1.1.post4.dist-info/RECORD
