Metadata-Version: 2.1
Name: partial-json-parser
Version: 0.2.1.1.post4
Summary: Parse partial JSON generated by LLM
Keywords: JSON,parser,LLM,nlp
Home-page: https://promplate.dev/partial-json-parser
Author-Email: Muspi Merol <me@promplate.dev>
License: MIT
Classifier: Development Status :: 5 - Production/Stable
Classifier: Intended Audience :: Developers
Project-URL: Repository, https://github.com/promplate/partial-json-parser
Project-URL: Homepage, https://promplate.dev/partial-json-parser
Requires-Python: >=3.6
Provides-Extra: playground
Requires-Dist: rich; extra == "playground"
